control4/__init__.py
control4/control4.py
python_control4_lite-0.1.15.dist-info/METADATA
python_control4_lite-0.1.15.dist-info/RECORD
python_control4_lite-0.1.15.dist-info/WHEEL
python_control4_lite-0.1.15.dist-info/top_level.txt
