Metadata-Version: 2.1
Name: python-control4-lite
Version: 0.1.15
Summary: Python Bindings for Control4 API
Home-page: https://github.com/r3pi/python-control4-lite
Author: Aleksi Asikainen
Author-email: aleksi.asikainen@solera.com
License: MIT
Keywords: control4
Platform: UNKNOWN
Requires-Python: >=3.6.0
Requires-Dist: aiohttp (>=3.0.0)
